<annotation>
    <folder>img_rotate</folder>
    <filename>maksssksksss320_flip.jpg</filename>
    <path>/Users/swift/Desktop/HTW/WissensManagement/2.semester/Abgabe/MaskDataSet/Mask/Mask/img_rotate/maksssksksss320_flip.jpg</path>
    <source>
        <database>Unknown</database>
    </source>
    <size>
        <width>400</width>
        <height>230</height>
        <depth>3</depth>
    </size>
    <segmented>0</segmented>
    <object>
        <name>without_mask</name>
        <pose>Unspecified</pose>
        <truncated>0</truncated>
        <difficult>0</difficult>
        <bndbox>
            <xmin>370</xmin>
            <ymin>51</ymin>
            <xmax>380</xmax>
            <ymax>64</ymax>
        </bndbox>
    </object>    <object>
        <name>with_mask</name>
        <pose>Unspecified</pose>
        <truncated>0</truncated>
        <difficult>0</difficult>
        <bndbox>
            <xmin>274</xmin>
            <ymin>21</ymin>
            <xmax>293</xmax>
            <ymax>44</ymax>
        </bndbox>
    </object>    <object>
        <name>with_mask</name>
        <pose>Unspecified</pose>
        <truncated>0</truncated>
        <difficult>0</difficult>
        <bndbox>
            <xmin>199</xmin>
            <ymin>89</ymin>
            <xmax>215</xmax>
            <ymax>108</ymax>
        </bndbox>
    </object>    <object>
        <name>with_mask</name>
        <pose>Unspecified</pose>
        <truncated>0</truncated>
        <difficult>0</difficult>
        <bndbox>
            <xmin>43</xmin>
            <ymin>10</ymin>
            <xmax>65</xmax>
            <ymax>36</ymax>
        </bndbox>
    </object>
</annotation>
